sphinx_toolbox/github/__init__.py
sphinx_toolbox/github/issues.py
sphinx_toolbox/github/repos_and_users.py
sphinx_toolbox/latex/__init__.py
sphinx_toolbox/latex/layout.py
sphinx_toolbox/latex/succinct_seealso.py
sphinx_toolbox/latex/toc.py
sphinx_toolbox/more_autodoc/__init__.py
sphinx_toolbox/more_autodoc/augment_defaults.py
sphinx_toolbox/more_autodoc/autonamedtuple.py
sphinx_toolbox/more_autodoc/autoprotocol.py
sphinx_toolbox/more_autodoc/autotypeddict.py
sphinx_toolbox/more_autodoc/generic_bases.py
sphinx_toolbox/more_autodoc/genericalias.py
sphinx_toolbox/more_autodoc/no_docstring.py
sphinx_toolbox/more_autodoc/overloads.py
sphinx_toolbox/more_autodoc/regex.py
sphinx_toolbox/more_autodoc/sourcelink.py
sphinx_toolbox/more_autodoc/typehints.py
sphinx_toolbox/more_autodoc/typevars.py
sphinx_toolbox/more_autodoc/variables.py
sphinx_toolbox/more_autosummary/__init__.py
sphinx_toolbox/more_autosummary/column_widths.py
sphinx_toolbox/tweaks/__init__.py
sphinx_toolbox/tweaks/footnote_symbols.py
sphinx_toolbox/tweaks/latex_layout.py
sphinx_toolbox/tweaks/latex_toc.py
sphinx_toolbox/tweaks/param_dash.py
sphinx_toolbox/tweaks/revert_footnote_style.py
sphinx_toolbox/tweaks/sphinx_panels_tabs.py
sphinx_toolbox/tweaks/tabsize.py
sphinx_toolbox/__init__.py
sphinx_toolbox/__main__.py
sphinx_toolbox/_css.py
sphinx_toolbox/_data_documenter.py
sphinx_toolbox/assets.py
sphinx_toolbox/cache.py
sphinx_toolbox/changeset.py
sphinx_toolbox/code.py
sphinx_toolbox/collapse.py
sphinx_toolbox/config.py
sphinx_toolbox/confval.py
sphinx_toolbox/decorators.py
sphinx_toolbox/documentation_summary.py
sphinx_toolbox/flake8.py
sphinx_toolbox/formatting.py
sphinx_toolbox/installation.py
sphinx_toolbox/issues.py
sphinx_toolbox/pre_commit.py
sphinx_toolbox/py.typed
sphinx_toolbox/rest_example.py
sphinx_toolbox/shields.py
sphinx_toolbox/sidebar_links.py
sphinx_toolbox/source.py
sphinx_toolbox/testing.py
sphinx_toolbox/utils.py
sphinx_toolbox/wikipedia.py
sphinx_toolbox-4.1.1.dist-info/LICENSE
sphinx_toolbox-4.1.1.dist-info/METADATA
sphinx_toolbox-4.1.1.dist-info/WHEEL
sphinx_toolbox-4.1.1.dist-info/entry_points.txt
sphinx_toolbox-4.1.1.dist-info/RECORD
