Metadata-Version: 2.2
Name: sphinx-toolbox
Version: 4.1.1
Summary: Box of handy tools for Sphinx 🧰 📔
Author-email: Dominic Davis-Foster <dominic@davis-foster.co.uk>
License: MIT
Keywords: documentation,sphinx,sphinx-extension
Home-page: https://github.com/sphinx-toolbox/sphinx-toolbox
Project-URL: Issue Tracker, https://github.com/sphinx-toolbox/sphinx-toolbox/issues
Project-URL: Source Code, https://github.com/sphinx-toolbox/sphinx-toolbox
Project-URL: Documentation, https://sphinx-toolbox.readthedocs.io/en/latest
Platform: Windows
Platform: macOS
Platform: Linux
Classifier: Development Status :: 5 - Production/Stable
Classifier: Framework :: Sphinx :: Extension
Classifier: Intended Audience :: Developers
Classifier: License :: OSI Approved :: MIT License
Classifier: Operating System :: OS Independent
Classifier: Programming Language :: Python
Classifier: Programming Language :: Python :: 3 :: Only
Classifier: Programming Language :: Python :: 3.7
Classifier: Programming Language :: Python :: 3.8
Classifier: Programming Language :: Python :: 3.9
Classifier: Programming Language :: Python :: 3.10
Classifier: Programming Language :: Python :: 3.11
Classifier: Programming Language :: Python :: 3.12
Classifier: Programming Language :: Python :: 3.13
Classifier: Programming Language :: Python :: Implementation :: CPython
Classifier: Programming Language :: Python :: Implementation :: PyPy
Classifier: Topic :: Documentation
Classifier: Topic :: Documentation :: Sphinx
Classifier: Topic :: Software Development :: Documentation
Classifier: Topic :: Software Development :: Libraries :: Python Modules
Classifier: Topic :: Utilities
Classifier: Typing :: Typed
Requires-Python: >=3.7
Requires-Dist: apeye>=0.4.0
Requires-Dist: autodocsumm>=0.2.0
Requires-Dist: beautifulsoup4>=4.9.1
Requires-Dist: cachecontrol[filecache]>=0.13.0
Requires-Dist: dict2css>=0.2.3
Requires-Dist: docutils>=0.16
Requires-Dist: domdf-python-tools>=2.9.0
Requires-Dist: filelock>=3.8.0
Requires-Dist: html5lib>=1.1
Requires-Dist: roman>4.0
Requires-Dist: ruamel.yaml<=0.18.16,>=0.16.12
Requires-Dist: sphinx>=3.2.0
Requires-Dist: sphinx-autodoc-typehints>=1.11.1
Requires-Dist: sphinx-jinja2-compat>=0.1.0
Requires-Dist: sphinx-prompt>=1.1.0
Requires-Dist: sphinx-tabs<3.4.7,>=1.2.1
Requires-Dist: tabulate>=0.8.7
Requires-Dist: typing-extensions!=3.10.0.1,>=3.7.4.3
Requires-Dist: typing-inspect>=0.6.0; python_version < "3.8"
Requires-Dist: coincidence>=0.4.3; extra == 'testing'
Requires-Dist: pygments<=2.13.0,>=2.7.4; extra == 'testing'
Requires-Dist: coincidence>=0.4.3; extra == 'all'
Requires-Dist: pygments<=2.13.0,>=2.7.4; extra == 'all'
Provides-Extra: testing
Provides-Extra: all
